expmeta/Batch.py
expmeta/Measurement.py
expmeta/__init__.py
expmeta/_version.py
expmeta-0.0.4.dist-info/LICENSE
expmeta-0.0.4.dist-info/METADATA
expmeta-0.0.4.dist-info/WHEEL
expmeta-0.0.4.dist-info/top_level.txt
expmeta-0.0.4.dist-info/RECORD
