Metadata-Version: 2.1
Name: expmeta
Version: 0.0.4
Summary: Python classes for working with measurement metadata for scientific experiments
Home-page: https://github.com/SamWolski/ExpMeta
Author: Sam Wolski
Author-email: wolski.samp@gmail.com
License: MIT
Platform: UNKNOWN
Classifier: Development Status :: 2 - Pre-Alpha
Classifier: Intended Audience :: Science/Research
Classifier: License :: OSI Approved :: MIT License
Classifier: Operating System :: OS Independent
Classifier: Programming Language :: Python :: 3.7
Classifier: Topic :: Scientific/Engineering
Requires-Python: >=3.7.*
Requires-Dist: pytest (>=6.2.3)
Requires-Dist: pandas (>=1.2.4)
